{"windows":[{"dataFineBando":"2022-10-21","nomeDellaMisura":"1.4.1 Esperienza del cittadino nei servizi pubblici","pagoPAappIO":"","dataFine":"2022-10-21","dataInizioBando":"2022-06-27","codiceBando":"a017Q00000ocbtrQAA","titolo":"1.4.1 Esperienza del Cittadino - Scuole - Giugno 2022","dataInizio":"2022-09-24"},{"dataFineBando":"2022-10-21","nomeDellaMisura":"1.2 Abilitazione e facilitazione migrazione al Cloud","pagoPAappIO":"","dataFine":"2022-10-21","dataInizioBando":"2022-06-27","codiceBando":"a017Q00000ocbtmQAA","titolo":"1.2 Abilitazione al Cloud - Scuole - Giugno 2022","dataInizio":"2022-09-24"},{"dataFineBando":"2022-10-28","nomeDellaMisura":"1.2 Abilitazione e facilitazione migrazione al Cloud","pagoPAappIO":"","dataFine":"2022-10-28","dataInizioBando":"2022-07-25","codiceBando":"a017Q00000uzQmzQAE","titolo":"1.2 Abilitazione al Cloud - Comuni - Luglio 2022","dataInizio":"2022-10-01"},{"dataFineBando":"2022-11-04","nomeDellaMisura":"1.4.1 Esperienza del cittadino nei servizi pubblici","pagoPAappIO":"","dataFine":"2022-11-04","dataInizioBando":"2022-09-19","codiceBando":"a017Q000017NZMCQA4","titolo":"1.4.1 Esperienza del Cittadino - Comuni - Settembre 2022","dataInizio":"2022-09-19"},{"dataFineBando":"2022-11-11","nomeDellaMisura":"1.4.5 Digitalizzazione degli avvisi pubblici","pagoPAappIO":"","dataFine":"2022-11-11","dataInizioBando":"2022-09-12","codiceBando":"a017Q000015cZ1KQAU","titolo":"1.4.5 \"Piattaforma Notifiche Digitali” Comuni (Settembre 2022)","dataInizio":"2022-10-12"},{"dataFineBando":"2022-11-25","nomeDellaMisura":"1.4.3 Adozione PagoPA e AppIO","pagoPAappIO":"PagoPA","dataFine":"2022-11-25","dataInizioBando":"2022-09-12","codiceBando":"a017Q000015cuUGQAY","titolo":"1.4.3 - pagoPA - Comuni - Settembre 2022","dataInizio":"2022-09-12"},{"dataFineBando":"2022-11-25","nomeDellaMisura":"1.4.4 Adozione identità digitale","pagoPAappIO":"","dataFine":"2022-11-25","dataInizioBando":"2022-09-12","codiceBando":"a017Q000015cmRzQAI","titolo":"1.4.4 Adozione SPID CIE  - Comuni - Settembre 2022","dataInizio":"2022-09-12"},{"dataFineBando":"2022-11-25","nomeDellaMisura":"1.4.3 Adozione PagoPA e AppIO","pagoPAappIO":"AppIO","dataFine":"2022-11-25","dataInizioBando":"2022-09-12","codiceBando":"a017Q000015cZ1UQAU","titolo":"1.4.3 - app IO - Comuni - Settembre 2022","dataInizio":"2022-09-12"},{"dataFineBando":"2023-01-13","nomeDellaMisura":"1.4.4 Adozione identità digitale","pagoPAappIO":"","dataFine":"2023-01-13","dataInizioBando":"2022-09-12","codiceBando":"a017Q000015cuUVQAY","titolo":"1.4.4 Adozione SPID CIE-Amm.ni diverse da Comuni e Scuole -  Settembre 2022","dataInizio":"2022-09-12"},{"dataFineBando":"2023-01-13","nomeDellaMisura":"1.4.3 Adozione PagoPA e AppIO","pagoPAappIO":"AppIO","dataFine":"2023-01-13","dataInizioBando":"2022-09-12","codiceBando":"a017Q000015cuUBQAY","titolo":"1.4.3 - app IO - Altri Enti - Settembre 2022","dataInizio":"2022-09-12"},{"dataFineBando":"2023-01-13","nomeDellaMisura":"1.4.3 Adozione PagoPA e AppIO","pagoPAappIO":"PagoPA","dataFine":"2023-01-13","dataInizioBando":"2022-09-12","codiceBando":"a017Q000015cuUHQAY","titolo":"1.4.3 - pagoPA - Altri Enti - Settembre 2022","dataInizio":"2022-09-12"}]}